[
  {
    "ticker": "XPR",
    "name": "XPR",
    "exchange": "빗썸",
    "entry_price": 3.494,
    "currency": "KRW",
    "entry_time": "2026-07-15 00:00"
  },
  {
    "ticker": "B3",
    "name": "B3",
    "exchange": "빗썸",
    "entry_price": 0.9581,
    "currency": "KRW",
    "entry_time": "2026-07-15 00:00"
  },
  {
    "ticker": "COS",
    "name": "COS",
    "exchange": "빗썸",
    "entry_price": 0.4983,
    "currency": "KRW",
    "entry_time": "2026-07-14 21:04",
    "signal": "trend"
  },
  {
    "ticker": "VANA",
    "name": "바나",
    "exchange": "업비트",
    "entry_price": 1933.0,
    "currency": "KRW",
    "entry_time": "2026-07-14 09:00"
  },
  {
    "ticker": "XEC",
    "name": "XEC",
    "exchange": "빗썸",
    "entry_price": 0.0098,
    "currency": "KRW",
    "entry_time": "2026-07-14 00:00"
  },
  {
    "ticker": "RED",
    "name": "RED",
    "exchange": "빗썸",
    "entry_price": 170.0,
    "currency": "KRW",
    "entry_time": "2026-07-14 00:00"
  },
  {
    "ticker": "BILL",
    "name": "BILL",
    "exchange": "빗썸",
    "entry_price": 87.36,
    "currency": "KRW",
    "entry_time": "2026-07-14 00:00"
  },
  {
    "ticker": "ELSA",
    "name": "ELSA",
    "exchange": "빗썸",
    "entry_price": 80.23,
    "currency": "KRW",
    "entry_time": "2026-07-14 00:00"
  },
  {
    "ticker": "MVC",
    "name": "MVC",
    "exchange": "빗썸",
    "entry_price": 1.762,
    "currency": "KRW",
    "entry_time": "2026-07-13 21:04",
    "signal": "trend"
  },
  {
    "ticker": "EPT",
    "name": "EPT",
    "exchange": "빗썸",
    "entry_price": 0.8052,
    "currency": "KRW",
    "entry_time": "2026-07-13 21:04",
    "signal": "trend"
  },
  {
    "ticker": "DCR",
    "name": "DCR",
    "exchange": "바이낸스",
    "entry_price": 12.23,
    "currency": "USDT",
    "entry_time": "2026-07-13 09:05",
    "signal": "trend"
  },
  {
    "ticker": "DODO",
    "name": "DODO",
    "exchange": "바이낸스",
    "entry_price": 0.02322,
    "currency": "USDT",
    "entry_time": "2026-07-13 09:05",
    "signal": "trend"
  }
]