{"prices": {"MOODENG_KRW": 56.18, "B3_KRW": 0.8049, "RED_KRW": 148.0, "PENDLE_KRW": 2251.0, "LINK_KRW": 12200.0, "POL_KRW": 121.0, "MANTRA_KRW": 9.686, "WIF_KRW": 225.0, "EUL_KRW": 1403.0, "COS_KRW": 0.3555, "FLOCK_KRW": 46.38, "VIRTUAL_KRW": 917.0, "VANA_KRW": 1674.0, "XPR_KRW": 3.665, "FF_KRW": 90.89, "WIF_USDT": 0.1538, "EUL_USDT": 0.963, "PORTO_USDT": 0.465, "CVX_USDT": 1.198, "DCR_USDT": 12.45, "DGB_USDT": 0.00365, "1000SATS_USDT": 9.43e-06, "PUMP_USDT": 0.001631, "GNO_USDT": 112.06, "LINK_USDT": 8.254, "PNUT_USDT": 0.0411, "CITY_USDT": 0.4, "VIC_USDT": 0.0373, "VIRTUAL_USDT": 0.6205}, "updated": "2026-07-18 15:29:01"}