{"prices": {"ELSA_KRW": 79.2, "EGLD_KRW": 4555.0, "BLAST_KRW": 0.5829, "T_KRW": 8.026, "ARB_KRW": 137.0, "DEXE_KRW": 71450.0, "BEAM_KRW": 2.345, "APE_KRW": 224.0, "SKL_KRW": 6.442, "SXT_KRW": 11.95, "WET_KRW": 96.4, "CAKE_KRW": 2103.0, "RED_KRW": 167.0, "WBETH_USDT": 1995.1, "HOLO_USDT": 0.0733, "TIA_USDT": 0.3949, "SKL_USDT": 0.00437, "SXT_USDT": 0.00813, "ZEC_USDT": 530.25, "POL_USDT": 0.08105, "NVDAB_USDT": 208.89, "TUT_USDT": 0.01253, "TRX_USDT": 0.3316, "PYR_USDT": 0.139, "RED_USDT": 0.1142}, "updated": "2026-07-13 11:29:02"}