{"prices": {"SYRUP_KRW": 242.0, "PUMP_KRW": 2.36, "CRO_KRW": 91.5, "BREV_KRW": 122.0, "SKY_KRW": 87.0, "ZBT_KRW": 205.0, "PEPE_KRW": 0.00411, "RAY_KRW": 1065.0, "MASK_KRW": 637.0, "ADA_KRW": 269.0, "MINA_KRW": 70.2, "SENT_KRW": 21.3, "BIRB_KRW": 107.0, "BONK_KRW": 0.00749, "ZKP_KRW": 80.15, "BSV_KRW": 21990.0, "AHT_KRW": 1.488, "ARPA_KRW": 15.4, "SOL_KRW": 123200.0, "PROM_USDT": 1.16, "TLM_USDT": 0.002719, "ARPA_USDT": 0.01022, "TRB_USDT": 16.14, "NOM_USDT": 0.00196, "NFP_USDT": 0.00556, "HMSTR_USDT": 0.0003685, "SNX_USDT": 0.233, "RPL_USDT": 1.77, "JST_USDT": 0.09019, "ORCA_USDT": 1.232, "BANANA_USDT": 3.072, "TSLAB_USDT": 402.7, "AI_USDT": 0.0214, "COOKIE_USDT": 0.0102, "SOL_USDT": 81.64, "SLP_USDT": 0.000546, "BNSOL_USDT": 91.3, "OPEN_USDT": 0.1619, "NMR_USDT": 9.58}, "updated": "2026-07-04 21:59:02"}