[
  {
    "ticker": "C98",
    "name": "C98",
    "exchange": "빗썸",
    "entry_price": 20.91,
    "currency": "KRW",
    "entry_time": "2026-07-12 09:05",
    "signal": "trend"
  },
  {
    "ticker": "ELSA",
    "name": "헤이엘사",
    "exchange": "업비트",
    "entry_price": 79.2,
    "currency": "KRW",
    "entry_time": "2026-07-12 09:00"
  },
  {
    "ticker": "PROM",
    "name": "PROM",
    "exchange": "바이낸스",
    "entry_price": 1.294,
    "currency": "USD",
    "entry_time": "2026-07-12 09:00"
  },
  {
    "ticker": "SXT",
    "name": "SXT",
    "exchange": "바이낸스",
    "entry_price": 0.00962,
    "currency": "USD",
    "entry_time": "2026-07-12 09:00"
  },
  {
    "ticker": "COW",
    "name": "카우프로토콜",
    "exchange": "업비트",
    "entry_price": 209.0,
    "currency": "KRW",
    "entry_time": "2026-07-12 09:00"
  },
  {
    "ticker": "T",
    "name": "T",
    "exchange": "빗썸",
    "entry_price": 6.94,
    "currency": "KRW",
    "entry_time": "2026-07-12 00:00"
  },
  {
    "ticker": "BEAM",
    "name": "BEAM",
    "exchange": "빗썸",
    "entry_price": 2.348,
    "currency": "KRW",
    "entry_time": "2026-07-12 00:00"
  },
  {
    "ticker": "MORPHO",
    "name": "MORPHO",
    "exchange": "빗썸",
    "entry_price": 3288.0,
    "currency": "KRW",
    "entry_time": "2026-07-12 00:00"
  },
  {
    "ticker": "FLUID",
    "name": "FLUID",
    "exchange": "빗썸",
    "entry_price": 1610.0,
    "currency": "KRW",
    "entry_time": "2026-07-12 00:00"
  },
  {
    "ticker": "EDGE",
    "name": "EDGE",
    "exchange": "빗썸",
    "entry_price": 102.0,
    "currency": "KRW",
    "entry_time": "2026-07-12 00:00"
  },
  {
    "ticker": "WET",
    "name": "WET",
    "exchange": "빗썸",
    "entry_price": 99.74,
    "currency": "KRW",
    "entry_time": "2026-07-12 00:00"
  },
  {
    "ticker": "PYR",
    "name": "PYR",
    "exchange": "빗썸",
    "entry_price": 267.0,
    "currency": "KRW",
    "entry_time": "2026-07-11 21:04",
    "signal": "trend"
  },
  {
    "ticker": "1MBABYDOGE",
    "name": "1MBABYDOGE",
    "exchange": "바이낸스",
    "entry_price": 0.0003271,
    "currency": "USDT",
    "entry_time": "2026-07-11 21:04",
    "signal": "trend"
  },
  {
    "ticker": "TUT",
    "name": "TUT",
    "exchange": "바이낸스",
    "entry_price": 0.01159,
    "currency": "USDT",
    "entry_time": "2026-07-11 09:06",
    "signal": "trend"
  }
]