{"prices": {"ELSA_KRW": 81.8, "BLAST_KRW": 0.5814, "ARB_KRW": 135.0, "T_KRW": 7.265, "EGLD_KRW": 4619.0, "CAKE_KRW": 2059.0, "WET_KRW": 94.7, "SKL_KRW": 6.577, "SXT_KRW": 12.13, "APE_KRW": 222.0, "RED_KRW": 164.0, "BEAM_KRW": 2.337, "DEXE_KRW": 69350.0, "PYR_USDT": 0.137, "TRX_USDT": 0.3306, "ZEC_USDT": 513.61, "SKL_USDT": 0.00447, "TIA_USDT": 0.3948, "NVDAB_USDT": 207.52, "SXT_USDT": 0.00828, "RED_USDT": 0.1123, "HOLO_USDT": 0.071, "POL_USDT": 0.08114, "WBETH_USDT": 1960.99, "TUT_USDT": 0.01219}, "updated": "2026-07-13 14:59:02"}