{"prices": {"BIRB_KRW": 109.0, "BONK_KRW": 0.00731, "ADA_KRW": 289.0, "MINA_KRW": 69.63, "ZBT_KRW": 198.0, "BREV_KRW": 122.0, "PUMP_KRW": 2.35, "ZKP_KRW": 77.21, "CRO_KRW": 91.8, "PEPE_KRW": 0.00412, "MASK_KRW": 626.0, "SYRUP_KRW": 242.0, "SKY_KRW": 85.45, "RAY_KRW": 1081.0, "BSV_KRW": 21440.0, "ARPA_KRW": 15.76, "SOL_KRW": 123300.0, "MIRA_KRW": 78.89, "OGN_KRW": 27.87, "ETHFI_KRW": 612.0, "TLM_USDT": 0.002417, "BANANA_USDT": 3.106, "NMR_USDT": 9.65, "ORCA_USDT": 1.239, "COOKIE_USDT": 0.0099, "RPL_USDT": 2.21, "SOL_USDT": 81.74, "NOM_USDT": 0.00194, "SLP_USDT": 0.000528, "ARPA_USDT": 0.01056, "JST_USDT": 0.09074, "SNX_USDT": 0.232, "PROM_USDT": 1.156, "TRB_USDT": 16.1, "HMSTR_USDT": 0.0003384, "BNSOL_USDT": 91.4, "NFP_USDT": 0.00721, "OPEN_USDT": 0.173}, "updated": "2026-07-05 08:59:01"}