{"prices": {"CRO_KRW": 88.33, "BEAM_KRW": 2.3, "SYRUP_KRW": 263.0, "PUMP_KRW": 2.47, "PEPE_KRW": 0.00407, "MASK_KRW": 639.0, "ZKP_KRW": 75.51, "MON_KRW": 37.13, "PYTH_KRW": 67.3, "MIRA_KRW": 72.81, "ZRX_KRW": 132.0, "IMX_KRW": 215.0, "XTZ_KRW": 371.0, "WIF_KRW": 255.0, "ADA_KRW": 276.0, "A_KRW": 112.0, "BCH_KRW": 363200.0, "BONK_KRW": 0.00676, "SUN_KRW": 26.75, "SAFE_KRW": 146.0, "MINA_KRW": 73.73, "BLUR_KRW": 30.5, "OGN_KRW": 25.21, "ARPA_KRW": 13.58, "ETHFI_KRW": 660.0, "SKY_KRW": 83.94, "YFI_KRW": 3865000.0, "OPEN_USDT": 0.1567, "HOT_USDT": 0.000347, "TRB_USDT": 16.89, "BEAMX_USDT": 0.001532, "MOVR_USDT": 1.526, "SLP_USDT": 0.000527, "MASK_USDT": 0.428, "ETHFI_USDT": 0.444, "OGN_USDT": 0.01697, "PROM_USDT": 1.135, "CAKE_USDT": 1.433, "VANRY_USDT": 0.008032, "PYTH_USDT": 0.04483, "YFI_USDT": 2599.0, "BAND_USDT": 0.1702, "GIGGLE_USDT": 27.86, "ORCA_USDT": 1.241, "BANANA_USDT": 3.131, "HMSTR_USDT": 0.0003652, "ARPA_USDT": 0.00912, "SNX_USDT": 0.224, "COOKIE_USDT": 0.0097, "JST_USDT": 0.0932, "GLMR_USDT": 0.0096}, "updated": "2026-07-07 10:29:02"}